ovos_tts_plugin_elevenlabs/__init__.py
ovos_tts_plugin_elevenlabs-0.1.0.dist-info/licenses/LICENSE
ovos_tts_plugin_elevenlabs-0.1.0.dist-info/METADATA
ovos_tts_plugin_elevenlabs-0.1.0.dist-info/WHEEL
ovos_tts_plugin_elevenlabs-0.1.0.dist-info/entry_points.txt
ovos_tts_plugin_elevenlabs-0.1.0.dist-info/top_level.txt
ovos_tts_plugin_elevenlabs-0.1.0.dist-info/RECORD
