Metadata-Version: 2.4
Name: ovos-tts-plugin-elevenlabs
Version: 0.1.0
Summary: OVOS TTS plugin for ElevenLabs text-to-speech API
Author: reklis
License: MIT
Project-URL: Homepage, https://github.com/reklis/ovos-tts-plugin-elevenlabs
Project-URL: Repository, https://github.com/reklis/ovos-tts-plugin-elevenlabs
Project-URL: Issues, https://github.com/reklis/ovos-tts-plugin-elevenlabs/issues
Keywords: ovos,openvoiceos,tts,text-to-speech,elevenlabs,plugin
Classifier: Development Status :: 4 - Beta
Classifier: Intended Audience :: Developers
Classifier: License :: OSI Approved :: MIT License
Classifier: Programming Language :: Python :: 3
Classifier: Programming Language :: Python :: 3.8
Classifier: Programming Language :: Python :: 3.9
Classifier: Programming Language :: Python :: 3.10
Classifier: Programming Language :: Python :: 3.11
Classifier: Programming Language :: Python :: 3.12
Classifier: Topic :: Multimedia :: Sound/Audio :: Speech
Requires-Python: >=3.8
License-File: LICENSE
Requires-Dist: ovos-plugin-manager>=0.0.1
Requires-Dist: requests>=2.25.0
Dynamic: license-file
